rasa/__init__.py
rasa/__main__.py
rasa/agents/__init__.py
rasa/agents/agent_factory.py
rasa/agents/agent_manager.py
rasa/agents/constants.py
rasa/agents/core/__init__.py
rasa/agents/core/agent_protocol.py
rasa/agents/core/types.py
rasa/agents/exceptions.py
rasa/agents/protocol/__init__.py
rasa/agents/protocol/a2a/__init__.py
rasa/agents/protocol/a2a/a2a_agent.py
rasa/agents/protocol/mcp/__init__.py
rasa/agents/protocol/mcp/mcp_base_agent.py
rasa/agents/protocol/mcp/mcp_open_agent.py
rasa/agents/protocol/mcp/mcp_task_agent.py
rasa/agents/schemas/__init__.py
rasa/agents/schemas/agent_input.py
rasa/agents/schemas/agent_output.py
rasa/agents/schemas/agent_tool_result.py
rasa/agents/schemas/agent_tool_schema.py
rasa/agents/templates/__init__.py
rasa/agents/templates/mcp_open_agent_prompt_template.jinja2
rasa/agents/templates/mcp_task_agent_prompt_template.jinja2
rasa/agents/utils.py
rasa/agents/validation.py
rasa/api.py
rasa/builder/README.md
rasa/builder/__init__.py
rasa/builder/auth.py
rasa/builder/config.py
rasa/builder/constants.py
rasa/builder/copilot/__init__.py
rasa/builder/copilot/constants.py
rasa/builder/copilot/copilot.py
rasa/builder/copilot/copilot_response_handler.py
rasa/builder/copilot/copilot_templated_message_provider.py
rasa/builder/copilot/exceptions.py
rasa/builder/copilot/history_store.py
rasa/builder/copilot/models.py
rasa/builder/copilot/prompts/__init__.py
rasa/builder/copilot/prompts/copilot_system_prompt.jinja2
rasa/builder/copilot/prompts/copilot_training_error_handler_prompt.jinja2
rasa/builder/copilot/prompts/latest_user_message_context_prompt.jinja2
rasa/builder/copilot/templated_messages/__init__.py
rasa/builder/copilot/templated_messages/copilot_internal_messages_templates.yml
rasa/builder/copilot/templated_messages/copilot_template_prompts.yml
rasa/builder/copilot/templated_messages/copilot_templated_responses.yml
rasa/builder/copilot/templated_messages/copilot_welcome_messages.yml
rasa/builder/document_retrieval/__init__.py
rasa_pro-3.15.5.dist-info/METADATA
rasa_pro-3.15.5.dist-info/NOTICE
rasa_pro-3.15.5.dist-info/WHEEL
rasa_pro-3.15.5.dist-info/entry_points.txt
rasa_pro-3.15.5.dist-info/RECORD
