Metadata-Version: 2.3
Name: rasa-pro
Version: 3.15.5
Summary: State-of-the-art open-core Conversational AI framework for Enterprises that natively leverages generative AI for effortless assistant development.
Keywords: nlp,machine-learning,machine-learning-library,bot,bots,botkit,rasa conversational-agents,conversational-ai,chatbot,chatbot-framework,bot-framework
Author: Rasa Technologies GmbH
Author-email: hi@rasa.com
Maintainer: Tom Bocklisch
Maintainer-email: tom@rasa.com
Requires-Python: >=3.10.0,<3.14
Classifier: Development Status :: 5 - Production/Stable
Classifier: Intended Audience :: Developers
Classifier: Programming Language :: Python :: 3
Classifier: Programming Language :: Python :: 3.10
Classifier: Programming Language :: Python :: 3.11
Classifier: Programming Language :: Python :: 3.12
Classifier: Programming Language :: Python :: 3.13
Classifier: Topic :: Software Development :: Libraries
Provides-Extra: channels
Provides-Extra: full
Provides-Extra: gh-release-notes
Provides-Extra: jieba
Provides-Extra: metal
Provides-Extra: monitoring
Provides-Extra: nlu
Provides-Extra: pii
Provides-Extra: spacy
Provides-Extra: transformers
Requires-Dist: CacheControl (>=0.14.2,<0.15.0)
Requires-Dist: PyJWT[crypto] (>=2.8.0,<3.0.0)
Requires-Dist: SQLAlchemy (>=2.0.42,<2.1.0)
Requires-Dist: a2a-sdk (>=0.3.4,<0.4.0)
Requires-Dist: absl-py (>=2.3.1,<2.4)
Requires-Dist: aio-pika (>=8.2.3,<9.4.4)
Requires-Dist: aiogram (>=3.22.0,<3.23.0) ; extra == "full" or extra == "channels"
Requires-Dist: aiohttp (>=3.10,<3.11)
Requires-Dist: aioshutil (>=1.5,<1.6)
Requires-Dist: apscheduler (>=3.11,<3.12)
Requires-Dist: attrs (>=23.1,<25.0)
Requires-Dist: audioop-lts (>=0.2.2,<0.3.0) ; python_version >= "3.13"
Requires-Dist: aws-msk-iam-sasl-signer-python (>=1.0.2,<1.1.0)
Requires-Dist: azure-identity (>=1.25.1,<1.26.0)
Requires-Dist: azure-storage-blob (>=12.27.0,<12.28.0)
Requires-Dist: boto3 (>=1.40.60,<1.41.0)
Requires-Dist: certifi (>=2025.10.5,<2025.11.0)
Requires-Dist: colorama (>=0.4.6,<0.5.0) ; sys_platform == "win32"
Requires-Dist: colorclass (>=2.2,<2.3)
Requires-Dist: coloredlogs (>=15,<16)
Requires-Dist: colorhash (>=2.0,<2.1.0)
Requires-Dist: confluent-kafka (>=2.11.0,<3.0.0)
Requires-Dist: cryptography (>=46.0.3,<46.1.0)
Requires-Dist: cvg-python-sdk (>=0.5.1,<0.6.0) ; extra == "full" or extra == "channels"
Requires-Dist: dask (>=2024.8.0,<2024.9.0)
Requires-Dist: demoji (>=1.1.0,<2.0.0)
Requires-Dist: diskcache (>=5.6.3,<5.7.0)
Requires-Dist: dnspython (==2.6.1)
Requires-Dist: faiss-cpu (>=1.11.0,<1.12.0)
Requires-Dist: fbmessenger (>=6.0.0,<6.1.0) ; extra == "full" or extra == "channels"
Requires-Dist: github3.py (>=3.2.0,<3.3.0) ; extra == "gh-release-notes"
Requires-Dist: gitpython (>=3.1.41,<3.2.0) ; extra == "full"
Requires-Dist: gliner (>=0.2.20,<0.3.0) ; extra == "full" or extra == "pii"
Requires-Dist: google-auth (>=2.41.1,<2.42.0)
Requires-Dist: google-cloud-storage (>=3.4.1,<3.5.0)
Requires-Dist: hvac (>=2.3.0,<2.4.0)
Requires-Dist: importlib-metadata (>=8.5.0,<8.6.0)
Requires-Dist: importlib-resources (>=6.5.2,<7.0.0)
Requires-Dist: jieba (>=0.42.1,<0.43) ; extra == "jieba" or extra == "full" or extra == "nlu"
Requires-Dist: jinja2 (>=3.1.6,<3.2.0)
Requires-Dist: jsonpatch (>=1.33,<2.0)
Requires-Dist: jsonpickle (>=3.3.0,<3.4)
Requires-Dist: jsonschema (>=4.22)
Requires-Dist: keras (>=3.12.0,<3.13.0)
Requires-Dist: langchain (>=0.3.27,<0.4.0)
Requires-Dist: langchain-community (>=0.3.29,<0.4.0)
Requires-Dist: langchain-core (>=0.3.80,<0.4.0)
Requires-Dist: langcodes[data] (>=3.5.1,<3.6.0)
Requires-Dist: langfuse (>=3.8.1,<3.9.0) ; extra == "full" or extra == "monitoring"
Requires-Dist: litellm (>=1.79.3,<1.80.0)
Requires-Dist: matplotlib (>=3.9.4,<3.10.0)
Requires-Dist: mattermostwrapper (>=2.2,<2.3) ; extra == "full" or extra == "channels"
Requires-Dist: mcp (>=1.23.0,<1.24.0)
Requires-Dist: mitie (>=0.7.36,<0.8.0) ; extra == "full" or extra == "nlu"
Requires-Dist: networkx (>=3.1,<3.2)
Requires-Dist: numpy (>=2.1.3,<2.2.0)
Requires-Dist: onnxruntime (==1.22.1) ; extra == "full" or extra == "pii"
Requires-Dist: openai (>=1.99.5,<1.100.0)
Requires-Dist: openpyxl (>=3.1.5,<4.0.0)
Requires-Dist: opentelemetry-api (>=1.33.0,<1.34.0)
Requires-Dist: opentelemetry-exporter-otlp (>=1.33.0,<1.34.0)
Requires-Dist: opentelemetry-sdk (>=1.33.0,<1.34.0)
Requires-Dist: packaging (>=23.2,<23.3)
Requires-Dist: pep440-version-utils (>=1.2.0,<1.3.0)
Requires-Dist: pluggy (>=1.2.0,<2.0.0)
Requires-Dist: portalocker (>=2.7.0,<3.0.0)
Requires-Dist: prompt-toolkit (>=3.0.28,<3.0.29)
Requires-Dist: protobuf (>=5.29.5,<5.30.0)
Requires-Dist: psutil (>=5.9.5,<6.0.0)
Requires-Dist: psycopg2-binary (>=2.9.10,<2.10.0)
Requires-Dist: pydot (>=1.4,<1.5)
Requires-Dist: pykwalify (>=1.8,<1.9)
Requires-Dist: pymilvus (>=2.6.1,<3.0.0)
Requires-Dist: pymongo (>=4.10.1,<4.11.0)
Requires-Dist: pypred (>=0.4.0,<0.5.0)
Requires-Dist: python-dateutil (>=2.8.2,<2.9.0)
Requires-Dist: python-dotenv (>=1.0.1,<2.0.0)
Requires-Dist: python-engineio (>=4.12.2,<4.13.0)
Requires-Dist: python-keycloak (>=5.8.1,<5.9.0)
Requires-Dist: python-socketio (>=5.14.0,<5.15.0)
Requires-Dist: pytz (>=2022.7.1,<2023.0)
Requires-Dist: pyyaml (>=6.0.2,<6.1.0)
Requires-Dist: qdrant-client (>=1.9.1,<1.10.0)
Requires-Dist: questionary (>=2.1.1,<2.2.0)
Requires-Dist: randomname (>=0.2.1,<0.3.0)
Requires-Dist: rasa-sdk (==3.15.0)
Requires-Dist: redis (>=4.6.0,<6.0)
Requires-Dist: regex (>=2024.7.24,<2024.8.0)
Requires-Dist: requests (>=2.32.5,<2.33.0)
Requires-Dist: rich (>=14.1.0,<14.2.0)
Requires-Dist: rocketchat_API (>=1.32.0,<1.33.0) ; extra == "full" or extra == "channels"
Requires-Dist: ruamel.yaml (>=0.17.21,<0.17.22)
Requires-Dist: safetensors (>=0.4.5,<0.5.0)
Requires-Dist: sanic (>=22.12,<22.13)
Requires-Dist: sanic-cors (>=2.2.0,<2.3.0)
Requires-Dist: sanic-jwt (>=1.8.0,<2.0.0)
Requires-Dist: sanic-openapi (>=21.12.0,<22.0.0)
Requires-Dist: sanic-routing (>=22.8.0,<23.0.0)
Requires-Dist: scikit-learn (>=1.6.1,<1.7.0)
Requires-Dist: scipy (>=1.13.1,<1.14.0) ; python_version < "3.12"
Requires-Dist: scipy (>=1.14.0,<1.15.0) ; python_version >= "3.12"
Requires-Dist: sentencepiece (>=0.1.99,<0.2.0) ; (python_version < "3.12") and (extra == "transformers" or extra == "full" or extra == "full" or extra == "nlu")
Requires-Dist: sentry-sdk (>=2.35.2,<2.36.0)
Requires-Dist: setuptools (>=78.1.1,<78.2.0)
Requires-Dist: sklearn-crfsuite (>=0.5.0,<0.6.0) ; extra == "full" or extra == "nlu"
Requires-Dist: skops (>=0.13.0,<0.14.0) ; extra == "full" or extra == "nlu"
Requires-Dist: slack-sdk (>=3.37.0,<3.38.0) ; extra == "full" or extra == "channels"
Requires-Dist: spacy (>=3.5.4,<4.0.0) ; extra == "spacy" or extra == "full" or extra == "nlu"
Requires-Dist: starlette (>=0.49.1,<0.50.0)
Requires-Dist: structlog (>=25.4.0,<25.5.0)
Requires-Dist: structlog-sentry (>=2.2.1,<2.3.0)
Requires-Dist: tarsafe (>=0.0.5,<0.0.6)
Requires-Dist: tenacity (>=8.4.1,<8.5.0)
Requires-Dist: tensorflow (>=2.19.0,<3.0.0) ; (sys_platform != "darwin" or platform_machine != "arm64" and python_version < "3.12") and (extra == "full" or extra == "nlu")
Requires-Dist: tensorflow-hub (>=0.16.0,<0.17.0) ; (python_version < "3.12") and (extra == "full" or extra == "nlu")
Requires-Dist: tensorflow-io-gcs-filesystem (==0.31) ; (sys_platform == "win32" and python_version < "3.12") and (extra == "full" or extra == "nlu")
Requires-Dist: tensorflow-io-gcs-filesystem (==0.34) ; (sys_platform == "darwin" and platform_machine != "arm64" and python_version < "3.12") and (extra == "full" or extra == "nlu")
Requires-Dist: tensorflow-io-gcs-filesystem (==0.34) ; (sys_platform == "linux" and python_version < "3.12") and (extra == "full" or extra == "nlu")
Requires-Dist: tensorflow-metal (>=1.2.0,<2.0.0) ; (sys_platform == "darwin" and platform_machine == "arm64" and python_version < "3.12") and (extra == "full" or extra == "metal" or extra == "nlu")
Requires-Dist: tensorflow-text (>=2.19.0,<3.0.0) ; (sys_platform != "win32" and platform_machine != "arm64" and platform_machine != "aarch64" and python_version < "3.12") and (extra == "full" or extra == "nlu")
Requires-Dist: terminaltables (>=3.1.10,<3.2.0)
Requires-Dist: tf-keras (>=2.15.0,<3.0.0) ; (python_version < "3.12") and (extra == "full" or extra == "nlu")
Requires-Dist: tiktoken (>=0.9.0,<0.10.0)
Requires-Dist: tqdm (>=4.66.2,<5.0.0)
Requires-Dist: transformers (>=4.53.0,<4.54.0) ; extra == "transformers" or extra == "full" or extra == "nlu"
Requires-Dist: twilio (>=9.8.4,<9.9.0) ; extra == "full" or extra == "channels"
Requires-Dist: types-cachetools (>=6.2.0.20250827,<6.3.0.0)
Requires-Dist: types-protobuf (==4.25.0.20240417)
Requires-Dist: typing-extensions (>=4.7.1,<5.0.0)
Requires-Dist: typing-utils (>=0.1.0,<0.2.0)
Requires-Dist: ujson (>=5.8,<6.0)
Requires-Dist: webexteamssdk (>=1.6.1,<1.7.0) ; extra == "full" or extra == "channels"
Requires-Dist: websockets (>=10.4,<11.0)
Requires-Dist: werkzeug (>=3.1.3,<4.0.0)
Requires-Dist: wheel (>=0.40.0)
Project-URL: Documentation, https://rasa.com/docs
Project-URL: Homepage, https://rasa.com
Project-URL: Repository, https://github.com/rasahq/rasa
